{
  "sector": {
    "id": 100,
    "type": "list",
    "attr": {
      "sctr": 0
    },
    "data": [
      {
        "id": 100,
        "type": "text",
        "text": "The real economy concerns the flow of goods and services (like oil, bread and labor hours), compared with the monetary sector that covers the circulation of money.",
        "is_banner": true,
        "action": {
          "type": "dismiss",
          "name": "Got it!"
        }
      },
      {
        "id": 100,
        "type": "list",
        "data": [
          {
            "id": 1,
            "type": "text",
            "title": "Tourism"
          },
          {
            "id": 2,
            "type": "img",
            "res": "tourism_banner"
          },
          {
            "id": 3,
            "type": "text",
            "text": "The tourism sector continues it’s resilient growth with start of two new airlines from China and Australia."
          },
          {
            "id": 100,
            "type": "list",
            "data": [
              {
                "id": 100,
                "type": "val",
                "name": "tourist arrivals",
                "date": "2019-12-01",
                "value": 129923,
                "scale": "k",
                "is_flow": true,
                "unit": "tourists",
                "pch": 0.12,
                "pch_intvl": "m",
                "show_chart": true,
                "action": {
                  "type": "open",
                  "api": "data"
                },
                "attr": {
                  "sctr": 2
                }
              },
              {
                "id": 100,
                "type": "comp",
                "name": "tourist arrivals",
                "date": "2019-12-01",
                "comp": {
                  "Food": 0.38,
                  "Housing": 0.29,
                  "Clothing": 0.11,
                  "Utility": 0.09,
                  "Health": 0.08,
                  "Other": 0.05
                },
                "action": {
                  "type": "open",
                  "api": "data"
                }
              },
              {
                "id": 100,
                "type": "chg",
                "name": "tourist arrivals",
                "date": "2019-12-01",
                "chg": 13101,
                "chg_intvl": "a",
                "scale": "k",
                "unit": "tourists",
                "action": {
                  "type": "open",
                  "api": "data"
                }
              }
            ]
          }
        ]
      },
      {
        "id": 100,
        "type": "list",
        "data": [
          {
            "id": 1,
            "type": "text",
            "title": "Inflation"
          },
          {
            "id": 2,
            "type": "img",
            "res": "inflation_banner"
          },
          {
            "id": 3,
            "type": "text",
            "text": "Quid ex ea voluptate et caritatem, quae dices, libenter assentiar probabo, inquit, modo ista sis aequitate, quam interrogare aut voluptates omittantur maiorum dolorum effugiendorum gratia  ex eo delectu rerum, quem modo dixi, constituto, ut labore et accurate disserendum et dolore disputandum putant sed ut."
          },
          {
            "id": 100,
            "type": "list",
            "attr:": {
              "scroll": "h",
              "sctr": "2"
            },
            "data": [
              {
                "id": 100,
                "type": "val",
                "name": "inflation",
                "date": "2019-12-01",
                "value": 0.124,
                "scale": "o",
                "is_flow": false,
                "unit": "percent",
                "action": {
                  "type": "open",
                  "api": "data"
                }
              },
              {
                "id": 100,
                "type": "chg",
                "name": "inflation",
                "date": "2019-12-01",
                "chg": 0.012,
                "chg_intvl": "m",
                "scale": "o",
                "unit": "percent",
                "action": {
                  "type": "open",
                  "api": "data"
                }
              },
              {
                "id": 100,
                "type": "chg",
                "name": "inflation",
                "date": "2019-12-01",
                "chg": -0.013,
                "chg_intvl": "a",
                "scale": "o",
                "unit": "percent",
                "action": {
                  "type": "open",
                  "api": "data"
                }
              },
              {
                "id": 100,
                "type": "comp",
                "name": "inflation",
                "date": "2019-12-01",
                "comp": {
                  "Food": 0.38,
                  "Housing": 0.29,
                  "Clothing": 0.11,
                  "Utility": 0.09,
                  "Health": 0.08,
                  "Other": 0.05
                },
                "action": {
                  "type": "open",
                  "api": "data"
                }
              }
            ]
          }
        ]
      }
    ]
  },
  "series": {
    "type": "page",
    "data": {
      "id": 100,
      "name": "Tourist arrivals",
      "sctr": "0",
      "path": [
        "Tourism"
      ],
      "unit": "tourists",
      "freq": "m",
      "is_flow": true,
      "ts_date": "2018-12-01",
      "ts": [
        150818,
        151552,
        168583,
        162843,
        163114,
        103022,
        113475,
        132144,
        139338,
        117619,
        141928,
        137921,
        171348
      ],
      "comp": {
        "m": {
          "2018-11-01": {
            "China": 0.38,
            "UK": 0.29,
            "Germany": 0.11,
            "Russia": 0.09,
            "Australia": 0.08,
            "Other": 0.05
          }
        },
        "q": {
          "2018-09-01": {
            "China": 0.38,
            "UK": 0.29,
            "Germany": 0.11,
            "Russia": 0.09,
            "Australia": 0.08,
            "Other": 0.05
          }
        },
        "a": {
          "2019-12-01": {
            "China": 0.38,
            "UK": 0.29,
            "Germany": 0.11,
            "Russia": 0.09,
            "Australia": 0.08,
            "Other": 0.05
          }
        }
      },
      "source": "Ministry of Tourism",
      "note": {
        "id": 1,
        "title": "Definition of tourist arrival",
        "text": "Quid ex eo ortum, tam..."
      },
      "qa": {
        "id": 1,
        "title": "Tum dicere exorsus...",
        "text": "Quid ex eo ortum, tam..."
      }
    }
  }
}